{
  "categories": [
    {
      "id": 1,
      "name": "",
      "display_name": "",
      "description": ""
    },
    {
      "name": "charles",
      "display_name": "big pappa",
      "description": "I don't know about that guy...",
      "id": 2
    }
  ],
  "products": [
    {
      "id": "1",
      "category": "",
      "name": "",
      "display_name": "",
      "description": ""
    },
    {
      "category": "food",
      "name": "orange",
      "display_name": "yellow",
      "description": "bad",
      "id": 4
    },
    {
      "category": "food",
      "name": "pink",
      "display_name": "yellow",
      "description": "ripe",
      "id": 6
    }
  ]
}